{"_ts":[1541055024,1541098556],"_r":{"breakdown":{"html":{"bytes":[8387,8385],"requests":[4,4]},"js":{"bytes":[591119,591369],"requests":[14,14]},"css":{"bytes":[75931,75954],"requests":[6,6]},"image":{"bytes":[811593,811594],"requests":[32,32]},"flash":{"bytes":[0,0],"requests":[0,0]},"font":{"bytes":[145852,145852],"requests":[6,6]},"video":{"bytes":[0,0],"requests":[0,0]},"other":{"bytes":[943,943],"requests":[3,3]}},"date":[1541055024,1541098556],"domElements":[417,417],"domInteractive":[2208,2059],"firstPaint":[919.8999999935,891.6000000008],"fullyLoaded":[6098,6079],"id":["181101_GB_ef6c68628ef2840ed2cecf4d062eeaa9","181101_VA_52b8df3c03d4e42a0b7ab1e890dbac7a"],"loadTime":[3644,3593],"render":[900,900],"SpeedIndex":[2362,2253],"TTFB":[324,313],"videoFrames":[[{"_i":"ms_000000.jpg","_t":0,"_vc":0},{"_i":"ms_000900.jpg","_t":900,"_vc":8},{"_i":"ms_001000.jpg","_t":1000,"_vc":9},{"_i":"ms_001200.jpg","_t":1200,"_vc":8},{"_i":"ms_001300.jpg","_t":1300,"_vc":8},{"_i":"ms_001400.jpg","_t":1400,"_vc":8},{"_i":"ms_001700.jpg","_t":1700,"_vc":8},{"_i":"ms_002200.jpg","_t":2200,"_vc":29},{"_i":"ms_002400.jpg","_t":2400,"_vc":92},{"_i":"ms_003000.jpg","_t":3000,"_vc":92},{"_i":"ms_003100.jpg","_t":3100,"_vc":92},{"_i":"ms_003200.jpg","_t":3200,"_vc":92},{"_i":"ms_003400.jpg","_t":3400,"_vc":92},{"_i":"ms_003600.jpg","_t":3600,"_vc":92},{"_i":"ms_003700.jpg","_t":3700,"_vc":92},{"_i":"ms_003800.jpg","_t":3800,"_vc":95},{"_i":"ms_003900.jpg","_t":3900,"_vc":96},{"_i":"ms_004000.jpg","_t":4000,"_vc":98},{"_i":"ms_004100.jpg","_t":4100,"_vc":99},{"_i":"ms_004200.jpg","_t":4200,"_vc":99},{"_i":"ms_004300.jpg","_t":4300,"_vc":99},{"_i":"ms_004400.jpg","_t":4400,"_vc":100}],[{"_i":"ms_000000.jpg","_t":0,"_vc":0},{"_i":"ms_000900.jpg","_t":900,"_vc":8},{"_i":"ms_001000.jpg","_t":1000,"_vc":9},{"_i":"ms_001200.jpg","_t":1200,"_vc":8},{"_i":"ms_001300.jpg","_t":1300,"_vc":8},{"_i":"ms_001400.jpg","_t":1400,"_vc":8},{"_i":"ms_001500.jpg","_t":1500,"_vc":8},{"_i":"ms_001600.jpg","_t":1600,"_vc":8},{"_i":"ms_001700.jpg","_t":1700,"_vc":19},{"_i":"ms_002100.jpg","_t":2100,"_vc":18},{"_i":"ms_002300.jpg","_t":2300,"_vc":92},{"_i":"ms_002900.jpg","_t":2900,"_vc":92},{"_i":"ms_003100.jpg","_t":3100,"_vc":92},{"_i":"ms_003200.jpg","_t":3200,"_vc":92},{"_i":"ms_003500.jpg","_t":3500,"_vc":92},{"_i":"ms_003600.jpg","_t":3600,"_vc":92},{"_i":"ms_003700.jpg","_t":3700,"_vc":93},{"_i":"ms_003800.jpg","_t":3800,"_vc":96},{"_i":"ms_003900.jpg","_t":3900,"_vc":97},{"_i":"ms_004000.jpg","_t":4000,"_vc":98},{"_i":"ms_004100.jpg","_t":4100,"_vc":99},{"_i":"ms_004200.jpg","_t":4200,"_vc":99},{"_i":"ms_004300.jpg","_t":4300,"_vc":99},{"_i":"ms_004400.jpg","_t":4400,"_vc":100}]],"visualComplete":[4400,4400],"lighthouse":[19,19],"pagespeed":[64,64]}}